lamden/__init__.py
lamden/__main__.py
lamden/authentication.py
lamden/db_config.py
lamden/network.py
lamden/rewards.py
lamden/router.py
lamden/storage.py
lamden/upgrade.py
lamden/cli/__init__.py
lamden/cli/cmd.py
lamden/cli/pkg.py
lamden/cli/start.py
lamden/contracts/__init__.py
lamden/contracts/genesis.json
lamden/contracts/submission.s.py
lamden/contracts/sync.py
lamden/contracts/genesis/__init__.py
lamden/contracts/genesis/currency.s.py
lamden/contracts/genesis/elect_members.s.py
lamden/contracts/genesis/election_house.s.py
lamden/contracts/genesis/foundation.s.py
lamden/contracts/genesis/members.s.py
lamden/contracts/genesis/rewards.s.py
lamden/contracts/genesis/stamp_cost.s.py
lamden/contracts/genesis/upgrade.s.py
lamden/crypto/__init__.py
lamden/crypto/canonical.py
lamden/crypto/transaction.py
lamden/crypto/wallet.py
lamden/crypto/zbase.py
lamden/formatting/__init__.py
lamden/formatting/primatives.py
lamden/formatting/rules.py
lamden/logger/__init__.py
lamden/logger/base.py
lamden/nodes/__init__.py
lamden/nodes/base.py
lamden/nodes/delegate/__init__.py
lamden/nodes/delegate/delegate.py
lamden/nodes/delegate/execution.py
lamden/nodes/delegate/work.py
lamden/nodes/masternode/__init__.py
lamden/nodes/masternode/contender.py
lamden/nodes/masternode/masternode.py
lamden/nodes/masternode/webserver.py
lamden-1.0.4.1.dist-info/LICENSE.txt
lamden-1.0.4.1.dist-info/METADATA
lamden-1.0.4.1.dist-info/WHEEL
lamden-1.0.4.1.dist-info/entry_points.txt
lamden-1.0.4.1.dist-info/top_level.txt
lamden-1.0.4.1.dist-info/RECORD
