Metadata-Version: 2.1
Name: lamden
Version: 1.0.4.1
Summary: Lamden Blockchain
Home-page: https://github.com/Lamden/lamden
Author: Lamden
Author-email: team@lamden.io
License: UNKNOWN
Platform: UNKNOWN
Classifier: Programming Language :: Python :: 3.6
Requires-Python: >=3.6.5
Requires-Dist: sanic
Requires-Dist: coloredlogs
Requires-Dist: pymongo
Requires-Dist: pyzmq
Requires-Dist: requests
Requires-Dist: contracting
Requires-Dist: checksumdir
Requires-Dist: pynacl
Requires-Dist: stdlib-list
